Metadata-Version: 2.1
Name: sonia
Version: 0.2.2
Summary: SONIA is a python 3.6 software developed to infer selection pressures on features of amino acid CDR3 sequences. The model can be used to calculate the probability of observing any sequence after selection and sample from the selected repertoire.
Author: Zachary Sethna
Author-email: Giulio Isacchini <giulioisac@gmail.com>
Maintainer-email: Giulio Isacchini <giulioisac@gmail.com>
License: GNU GENERAL PUBLIC LICENSE
Project-URL: Homepage, https://github.com/statbiophys/SONIA
Project-URL: Documentation, https://sonia-package.readthedocs.io/en/latest/
Classifier: Development Status :: 3 - Alpha
Classifier: Intended Audience :: Developers
Classifier: Intended Audience :: Healthcare Industry
Classifier: Intended Audience :: Science/Research
Classifier: Topic :: Scientific/Engineering :: Bio-Informatics
Classifier: Topic :: Scientific/Engineering :: Physics
Classifier: Topic :: Scientific/Engineering :: Medical Science Apps.
Classifier: License :: OSI Approved :: GNU General Public License v3 (GPLv3)
Classifier: Natural Language :: English
Classifier: Programming Language :: Python :: 3.6
License-File: LICENSE
Requires-Dist: numpy
Requires-Dist: tensorflow >=2.1.0
Requires-Dist: matplotlib
Requires-Dist: olga >=1.1.3
Requires-Dist: tqdm
